LICENSE
case_insensitive_dict/__init__.py
case_insensitive_dict/case_insensitive_dict.py
case_insensitive_dict/py.typed
case_insensitive_dictionary-0.2.0.dist-info/LICENSE
case_insensitive_dictionary-0.2.0.dist-info/WHEEL
case_insensitive_dictionary-0.2.0.dist-info/METADATA
case_insensitive_dictionary-0.2.0.dist-info/RECORD
