Metadata-Version: 2.1
Name: case-insensitive-dictionary
Version: 0.2.0
Summary: Typed Python Case Insensitive Dictionary
Home-page: https://github.com/DeveloperRSquared/case-insensitive-dict
License: MIT
Keywords: python,python3,dict,development,tooling,utils
Author: rikhilrai
Requires-Python: >=3.7,<4.0
Classifier: Development Status :: 5 - Production/Stable
Classifier: Intended Audience :: Developers
Classifier: License :: OSI Approved :: MIT License
Classifier: Operating System :: OS Independent
Classifier: Programming Language :: Python
Classifier: Programming Language :: Python :: 3
Classifier: Programming Language :: Python :: 3.10
Classifier: Programming Language :: Python :: 3.7
Classifier: Programming Language :: Python :: 3.8
Classifier: Programming Language :: Python :: 3.9
Classifier: Topic :: Software Development :: Build Tools
Classifier: Topic :: Software Development :: Libraries :: Python Modules
Classifier: Typing :: Typed
Requires-Dist: importlib-metadata (<4.3); python_version < "3.8"
Project-URL: Repository, https://github.com/DeveloperRSquared/case-insensitive-dict
